edge_ai/__init__.py
edge_ai/common/__init__.py
edge_ai/common/api.py
edge_ai/common/opts.py
edge_ai/common/utils.py
edge_ai/main.py
edge_ai/portals.py
edge_ai/transformations.py
edge_ai-0.1.2.dist-info/WHEEL
edge_ai-0.1.2.dist-info/entry_points.txt
edge_ai-0.1.2.dist-info/LICENSE.txt
edge_ai-0.1.2.dist-info/METADATA
edge_ai-0.1.2.dist-info/RECORD
