Metadata-Version: 2.1
Name: edge-ai
Version: 0.1.2
Summary: 
Author: Jorge Silva
Author-email: jorge@edgeimpulse.com
Requires-Python: >=3.10,<4.0
Classifier: Programming Language :: Python :: 3
Classifier: Programming Language :: Python :: 3.10
Classifier: Programming Language :: Python :: 3.11
Requires-Dist: pandas (>=1.5.3,<2.0.0)
Requires-Dist: requests (>=2.28.2,<3.0.0)
Requires-Dist: typer[all] (>=0.7.0,<0.8.0)
